LICENSE
MANIFEST.in
README.md
setup.cfg
setup.py
tap_sailthru/__init__.py
tap_sailthru/client.py
tap_sailthru/discover.py
tap_sailthru/streams.py
tap_sailthru/sync.py
tap_sailthru/transform.py
tap_sailthru.egg-info/PKG-INFO
tap_sailthru.egg-info/SOURCES.txt
tap_sailthru.egg-info/dependency_links.txt
tap_sailthru.egg-info/entry_points.txt
tap_sailthru.egg-info/requires.txt
tap_sailthru.egg-info/top_level.txt
tap_sailthru/schemas/ad_targeter_plans.json
tap_sailthru/schemas/blast_query.json
tap_sailthru/schemas/blast_repeats.json
tap_sailthru/schemas/blast_save_list.json
tap_sailthru/schemas/blasts.json
tap_sailthru/schemas/lists.json
tap_sailthru/schemas/purchase_log.json
tap_sailthru/schemas/users.json
tests/test_all_fields.py
tests/test_automatic_fields.py
tests/test_bookmark.py
tests/test_discovery.py
tests/test_start_date.py