Metadata-Version: 2.1
Name: tap-sailthru
Version: 1.0.0
Summary: Singer.io tap for the SailThru API
Home-page: http://singer.io
Author: Stitch
Classifier: Programming Language :: Python :: 3 :: Only
Provides-Extra: dev
License-File: LICENSE
